{
  "variant": "professional",
  "primary": "hsl(34, 33%, 75%)",
  "appearance": "light",
  "radius": 0.5,
  "colors": {
    "background": "hsl(34, 33%, 75%)",
    "foreground": "hsl(20, 29%, 28%)",
    "muted": "hsl(46, 33%, 91%)",
    "accent": "hsl(177, 48%, 46%)",
    "primary": {
      "default": "hsl(34, 33%, 75%)",
      "light": "hsl(34, 33%, 85%)",
      "dark": "hsl(34, 33%, 65%)"
    },
    "secondary": {
      "default": "hsl(177, 48%, 46%)",
      "light": "hsl(177, 48%, 56%)",
      "dark": "hsl(177, 48%, 36%)"
    },
    "wood": {
      "default": "hsl(20, 29%, 28%)",
      "light": "hsl(20, 29%, 38%)",
      "dark": "hsl(20, 29%, 18%)"
    }
  },
  "effects": {
    "shadows": {
      "sm": "0 1px 2px 0 rgb(92 64 51 / 0.1)",
      "md": "0 4px 6px -1px rgb(92 64 51 / 0.15)",
      "lg": "0 10px 15px -3px rgb(92 64 51 / 0.2)"
    },
    "gradients": {
      "wood": "linear-gradient(45deg, var(--wood-dark), var(--wood-light))",
      "sandstone": "linear-gradient(to right, var(--primary-light), var(--primary-dark))"
    }
  }
}